ichthyop/__init__.py
ichthyop/_connect_traj.py
ichthyop/connectivity.py
ichthyop/density.py
ichthyop/plot.py
ichthyop/read.py
ichthyop/shape.py
ichthyop-1.1.0.dist-info/LICENSE
ichthyop-1.1.0.dist-info/METADATA
ichthyop-1.1.0.dist-info/WHEEL
ichthyop-1.1.0.dist-info/top_level.txt
ichthyop-1.1.0.dist-info/RECORD
