Metadata-Version: 2.1
Name: ichthyop
Version: 1.1.0
Summary: Python package for the analysis of Ichthyop outputs
Home-page: https://github.com/ichthyop/ichthyop-python
Author: Ichthyop team
Author-email: nicolas.barrier@ird.fr
Maintainer: Nicolas Barrier
Maintainer-email: nicolas.barrier@ird.fr
License: UNKNOWN
Keywords: ocean; grid model; transport; lagrangian; larval dispersion; ichthyoplankton
Platform: linux
Platform: mac osx
Classifier: Development Status :: 4 - Beta
Classifier: Intended Audience :: Science/Research
Classifier: Topic :: Scientific/Engineering :: Mathematics
Classifier: Topic :: Scientific/Engineering :: Visualization
Classifier: License :: OSI Approved :: GNU General Public License v3 or later (GPLv3+)
Classifier: Operating System :: MacOS :: MacOS X
Classifier: Operating System :: Unix
Classifier: Operating System :: POSIX :: Linux
Classifier: Programming Language :: Python :: 2.7
Classifier: Programming Language :: Python :: 3
License-File: LICENSE
Requires-Dist: cartopy
Requires-Dist: matplotlib (>=1.4)
Requires-Dist: netCDF4 (>=1.1)
Requires-Dist: numpy (>=1.9)
Requires-Dist: pyshp
Requires-Dist: xarray (>=0.1)
